kat_bulgaria/__init__.py
kat_bulgaria/data_models.py
kat_bulgaria/errors.py
kat_bulgaria/helpers.py
kat_bulgaria/kat_api_client.py
kat_bulgaria-3.1.0.dist-info/licenses/LICENSE
kat_bulgaria-3.1.0.dist-info/METADATA
kat_bulgaria-3.1.0.dist-info/WHEEL
kat_bulgaria-3.1.0.dist-info/top_level.txt
kat_bulgaria-3.1.0.dist-info/RECORD
