Metadata-Version: 2.4
Name: kat_bulgaria
Version: 3.1.0
Summary: A library to check for existing obligations from KAT Bulgaria
Author-email: Nikola Nedevski <nikola.nedevski@gmail.com>
License: MIT
Project-URL: Homepage, https://github.com/Nedevski/py_kat_bulgaria
Project-URL: Issues, https://github.com/Nedevski/py_kat_bulgaria/issues
Project-URL: Repository, https://github.com/Nedevski/py_kat_bulgaria.git
Project-URL: Donate, https://ko-fi.com/nedevski/tip
Keywords: kat,mvr,bulgaria
Requires-Python: >=3.11
License-File: LICENSE
Requires-Dist: httpx
Dynamic: license-file
